<?xml version="1.0" encoding="utf-8"?>
<odb xmlns="http://ciax.sum.naoj.org/ciax-xml/odb">
  <object id="ml1" label="MOIRCS Temperature 1" class="lk8" client="socat - tcp:celaeno:4005" port="24105">
    <status xmlns="http://ciax.sum.naoj.org/ciax-xml/odbs">
      <title ref="ch0" label="MosCold2" />
      <title ref="ch1" label="MosCold1" />
      <title ref="ch2" label="Mask" />
      <title ref="ch3" label="Wheel" />
      <title ref="ch4" label="D1(NONE)" />
      <title ref="ch5" label="D2(NONE)" />
      <title ref="ch6" label="ChipBox1" />
      <title ref="ch7" label="Det1" />
      <title ref="sp" label="SetPoint1 (K)" />
      <title ref="htr" label="HeaterPower1(%%)" />
    </status>
  </object>
</odb>